acoustics_hardware/__init__.py
acoustics_hardware/_core.py
acoustics_hardware/_version.py
acoustics_hardware/analysis.py
acoustics_hardware/generators.py
acoustics_hardware/interfaces.py
acoustics_hardware/recorders.py
acoustics_hardware/serial.py
acoustics_hardware/signal_tools.py
acoustics_hardware/timestamps.py
acoustics_hardware/triggers.py
acoustics_hardware-0.2.1.dist-info/LICENSE
acoustics_hardware-0.2.1.dist-info/METADATA
acoustics_hardware-0.2.1.dist-info/WHEEL
acoustics_hardware-0.2.1.dist-info/top_level.txt
acoustics_hardware-0.2.1.dist-info/RECORD
