Metadata-Version: 2.1
Name: acoustics-hardware
Version: 0.2.1
Summary: Controlling hardware used in acoustic measurement systems
Home-page: https://github.com/AppliedAcousticsChalmers/acoustics-hardware
Author: Carl Andersson
Author-email: carl.andersson@chalmers.se
License: MIT
License-File: LICENSE
Requires-Dist: numpy
Requires-Dist: scipy
Requires-Dist: sounddevice
Requires-Dist: pyserial
Requires-Dist: SchunkMotionProtocol
Requires-Dist: zarr
Requires-Dist: nidaqmx ; platform_system == "Windows"
